fds/sdk/utils/__init__.py
fds/sdk/utils/authentication/__init__.py
fds/sdk/utils/authentication/confidential.py
fds/sdk/utils/authentication/constants.py
fds/sdk/utils/authentication/exceptions.py
fds/sdk/utils/authentication/oauth2client.py
fds_sdk_utils-2.1.2.dist-info/LICENSE
fds_sdk_utils-2.1.2.dist-info/METADATA
fds_sdk_utils-2.1.2.dist-info/WHEEL
fds_sdk_utils-2.1.2.dist-info/RECORD
