Metadata-Version: 2.3
Name: fds.sdk.utils
Version: 2.1.2
Summary: Utilities for interacting with FactSet APIs.
License: Apache-2.0
Keywords: FactSet,API,SDK
Author: FactSet Research Systems
Requires-Python: >=3.8.0,<4.0.0
Classifier: License :: OSI Approved :: Apache Software License
Classifier: Programming Language :: Python :: 3
Classifier: Programming Language :: Python :: 3.8
Classifier: Programming Language :: Python :: 3.9
Classifier: Programming Language :: Python :: 3.10
Classifier: Programming Language :: Python :: 3.11
Classifier: Programming Language :: Python :: 3.12
Classifier: Programming Language :: Python :: 3.13
Requires-Dist: joserfc (>=0.9,<1.2)
Requires-Dist: oauthlib (>=3.2.2,<4.0.0)
Requires-Dist: requests (>=2.28.2,<3.0.0)
Requires-Dist: requests-oauthlib (>=2.0.0,<3.0.0)
Project-URL: Homepage, https://developer.factset.com
